{
	"$schema": "https://schemas.wp.org/trunk/block.json",
	"apiVersion": 3,
	"name": "meomblocks/house-condition",
	"version": "0.1.0",
	"title": "Kohteen kuntopisteet",
	"category": "meomblocks",
	"keywords": [
		"artikkeli",
		"auto",
		"meomblocks"
	],
	"description": "Näyttää kohteen kuntopisteet.",
	"attributes": {},
	"example": {},
	"supports": {
		"html": false,
		"spacing": {
			"margin": [ "top" ]
		}
	},
	"textdomain": "meomblocks",
	"editorScript": "file:./index.js",
	"editorStyle": "file:./index.css",
	"style": "file:./style-index.css",
	"render": "file:./render.php"
}
